gitjudge/__init__.py
gitjudge/gitjudge.py
gitjudge/entity/__init__.py
gitjudge/entity/checkresult.py
gitjudge/entity/checks.py
gitjudge/entity/commit.py
gitjudge/entity/definition.py
gitjudge/entity/expected_commit.py
gitjudge/entity/repository.py
gitjudge/entity/validator.py
gitjudge/mapper/__init__.py
gitjudge/mapper/checks.py
gitjudge/mapper/definition.py
gitjudge/mapper/expected_commit.py
test/__init__.py
test/conftest.py
gitjudge-0.1.0.dist-info/METADATA
gitjudge-0.1.0.dist-info/WHEEL
gitjudge-0.1.0.dist-info/entry_points.txt
gitjudge-0.1.0.dist-info/top_level.txt
gitjudge-0.1.0.dist-info/RECORD
